topology_docker/__init__.py
topology_docker/networks.py
topology_docker/node.py
topology_docker/platform.py
topology_docker/shell.py
topology_docker/utils.py
topology_docker/nodes/__init__.py
topology_docker/nodes/host.py
topology_docker/nodes/switch.py
topology_docker-1.8.2.dist-info/licenses/LICENSE
topology_docker-1.8.2.dist-info/METADATA
topology_docker-1.8.2.dist-info/WHEEL
topology_docker-1.8.2.dist-info/entry_points.txt
topology_docker-1.8.2.dist-info/top_level.txt
topology_docker-1.8.2.dist-info/RECORD
