Metadata-Version: 2.4
Name: topology_docker
Version: 1.8.2
Summary: Docker based Platform Engine plugin for the Network Topology Framework.
Home-page: http://topology-docker.rtfd.org/
Author: Hewlett Packard Enterprise Development LP
Author-email: hpe-networking@lists.hp.com
Keywords: topology_docker
Classifier: Development Status :: 3 - Alpha
Classifier: Intended Audience :: Developers
Classifier: License :: OSI Approved :: Apache Software License
Classifier: Natural Language :: English
Classifier: Operating System :: POSIX :: Linux
Classifier: Programming Language :: Python :: 2
Classifier: Programming Language :: Python :: 2.7
Classifier: Programming Language :: Python :: 3
Classifier: Programming Language :: Python :: 3.4
License-File: LICENSE
Requires-Dist: six
Requires-Dist: docker
Requires-Dist: topology>=1.8.0
Requires-Dist: pyparsing
Dynamic: author
Dynamic: author-email
Dynamic: classifier
Dynamic: description
Dynamic: home-page
Dynamic: keywords
Dynamic: license-file
Dynamic: requires-dist
Dynamic: summary
